NSRPA/System.py
NSRPA/__init__.py
nsrpa-0.0.1.dist-info/METADATA
nsrpa-0.0.1.dist-info/WHEEL
nsrpa-0.0.1.dist-info/licenses/LICENCE.txt
nsrpa-0.0.1.dist-info/RECORD
